[
  {
    "close":0.03648
  },
  {
    "close":0.03683
  },
  {
    "close":0.03684
  },
  {
    "close":0.03673
  },
  {
    "close":0.03682
  },
  {
    "close":0.03703
  },
  {
    "close":0.03708
  },
  {
    "close":0.03717
  },
  {
    "close":0.03686
  },
  {
    "close":0.03671
  },
  {
    "close":0.03875
  },
  {
    "close":0.0381
  },
  {
    "close":0.03816
  },
  {
    "close":0.03776
  },
  {
    "close":0.03836
  },
  {
    "close":0.03788
  },
  {
    "close":0.03807
  },
  {
    "close":0.03766
  },
  {
    "close":0.03736
  },
  {
    "close":0.03755
  },
  {
    "close":0.038
  },
  {
    "close":0.0378
  },
  {
    "close":0.03806
  },
  {
    "close":0.03846
  },
  {
    "close":0.03901
  },
  {
    "close":0.03967
  },
  {
    "close":0.03868
  },
  {
    "close":0.03896
  },
  {
    "close":0.04015
  },
  {
    "close":0.04035
  }
]