[
  {
    "close":4.695
  },
  {
    "close":4.717
  },
  {
    "close":4.717
  },
  {
    "close":4.728
  },
  {
    "close":4.716
  },
  {
    "close":4.754
  },
  {
    "close":4.762
  },
  {
    "close":4.736
  },
  {
    "close":4.714
  },
  {
    "close":4.717
  },
  {
    "close":4.729
  },
  {
    "close":4.707
  },
  {
    "close":4.723
  },
  {
    "close":4.718
  },
  {
    "close":4.707
  },
  {
    "close":4.682
  },
  {
    "close":4.682
  },
  {
    "close":4.659
  },
  {
    "close":4.623
  },
  {
    "close":4.649
  },
  {
    "close":4.66
  },
  {
    "close":4.65
  },
  {
    "close":4.646
  },
  {
    "close":4.641
  },
  {
    "close":4.685
  },
  {
    "close":4.698
  },
  {
    "close":4.677
  },
  {
    "close":4.682
  },
  {
    "close":4.715
  },
  {
    "close":4.709
  }
]