[
  {
    "close":2.467
  },
  {
    "close":2.474
  },
  {
    "close":2.481
  },
  {
    "close":2.485
  },
  {
    "close":2.489
  },
  {
    "close":2.493
  },
  {
    "close":2.516
  },
  {
    "close":2.523
  },
  {
    "close":2.515
  },
  {
    "close":2.505
  },
  {
    "close":2.51
  },
  {
    "close":2.51
  },
  {
    "close":2.497
  },
  {
    "close":2.506
  },
  {
    "close":2.496
  },
  {
    "close":2.486
  },
  {
    "close":2.467
  },
  {
    "close":2.461
  },
  {
    "close":2.445
  },
  {
    "close":2.435
  },
  {
    "close":2.445
  },
  {
    "close":2.454
  },
  {
    "close":2.45
  },
  {
    "close":2.451
  },
  {
    "close":2.453
  },
  {
    "close":2.485
  },
  {
    "close":2.484
  },
  {
    "close":2.48
  },
  {
    "close":2.471
  },
  {
    "close":2.473
  }
]