[
  {
    "close":0.0994
  },
  {
    "close":0.09968
  },
  {
    "close":0.09985
  },
  {
    "close":0.10019
  },
  {
    "close":0.10021
  },
  {
    "close":0.10091
  },
  {
    "close":0.10135
  },
  {
    "close":0.10093
  },
  {
    "close":0.10053
  },
  {
    "close":0.10067
  },
  {
    "close":0.10098
  },
  {
    "close":0.10016
  },
  {
    "close":0.10044
  },
  {
    "close":0.10088
  },
  {
    "close":0.10056
  },
  {
    "close":0.09987
  },
  {
    "close":0.09956
  },
  {
    "close":0.09914
  },
  {
    "close":0.09847
  },
  {
    "close":0.09894
  },
  {
    "close":0.09911
  },
  {
    "close":0.09887
  },
  {
    "close":0.09875
  },
  {
    "close":0.09876
  },
  {
    "close":0.09981
  },
  {
    "close":0.09983
  },
  {
    "close":0.09938
  },
  {
    "close":0.09921
  },
  {
    "close":0.09989
  },
  {
    "close":0.09966
  }
]