[
  {
    "close":0.39297
  },
  {
    "close":0.39225
  },
  {
    "close":0.39006
  },
  {
    "close":0.39445
  },
  {
    "close":0.39391
  },
  {
    "close":0.39602
  },
  {
    "close":0.383
  },
  {
    "close":0.372
  },
  {
    "close":0.38388
  },
  {
    "close":0.37199
  },
  {
    "close":0.35456
  },
  {
    "close":0.34987
  },
  {
    "close":0.34529
  },
  {
    "close":0.34802
  },
  {
    "close":0.34992
  },
  {
    "close":0.33928
  },
  {
    "close":0.3398
  },
  {
    "close":0.33673
  },
  {
    "close":0.3303
  },
  {
    "close":0.33228
  },
  {
    "close":0.33632
  },
  {
    "close":0.33652
  },
  {
    "close":0.3388
  },
  {
    "close":0.33619
  },
  {
    "close":0.33336
  },
  {
    "close":0.33609
  },
  {
    "close":0.3344
  },
  {
    "close":0.33585
  },
  {
    "close":0.33738
  },
  {
    "close":0.33765
  }
]