[
  {
    "close":0.01723
  },
  {
    "close":0.01727
  },
  {
    "close":0.0173
  },
  {
    "close":0.01735
  },
  {
    "close":0.01736
  },
  {
    "close":0.01743
  },
  {
    "close":0.01742
  },
  {
    "close":0.01735
  },
  {
    "close":0.01733
  },
  {
    "close":0.01732
  },
  {
    "close":0.01738
  },
  {
    "close":0.01733
  },
  {
    "close":0.01737
  },
  {
    "close":0.01733
  },
  {
    "close":0.01731
  },
  {
    "close":0.01717
  },
  {
    "close":0.01712
  },
  {
    "close":0.017
  },
  {
    "close":0.01698
  },
  {
    "close":0.017
  },
  {
    "close":0.01704
  },
  {
    "close":0.01699
  },
  {
    "close":0.01699
  },
  {
    "close":0.017
  },
  {
    "close":0.01711
  },
  {
    "close":0.01717
  },
  {
    "close":0.0171
  },
  {
    "close":0.01703
  },
  {
    "close":0.01709
  },
  {
    "close":0.017
  }
]