[
  {
    "close":0.3253
  },
  {
    "close":0.3233
  },
  {
    "close":0.3207
  },
  {
    "close":0.3221
  },
  {
    "close":0.3227
  },
  {
    "close":0.3233
  },
  {
    "close":0.3249
  },
  {
    "close":0.3281
  },
  {
    "close":0.3232
  },
  {
    "close":0.3216
  },
  {
    "close":0.32
  },
  {
    "close":0.32
  },
  {
    "close":0.3186
  },
  {
    "close":0.3188
  },
  {
    "close":0.3224
  },
  {
    "close":0.3202
  },
  {
    "close":0.3174
  },
  {
    "close":0.316
  },
  {
    "close":0.3162
  },
  {
    "close":0.3187
  },
  {
    "close":0.3213
  },
  {
    "close":0.3181
  },
  {
    "close":0.3233
  },
  {
    "close":0.3281
  },
  {
    "close":0.3298
  },
  {
    "close":0.331
  },
  {
    "close":0.3322
  },
  {
    "close":0.3287
  },
  {
    "close":0.3338
  },
  {
    "close":0.333
  }
]