[
  {
    "close":0.2302
  },
  {
    "close":0.2304
  },
  {
    "close":0.23
  },
  {
    "close":0.2308
  },
  {
    "close":0.2306
  },
  {
    "close":0.2319
  },
  {
    "close":0.2324
  },
  {
    "close":0.2317
  },
  {
    "close":0.2311
  },
  {
    "close":0.2316
  },
  {
    "close":0.2319
  },
  {
    "close":0.2313
  },
  {
    "close":0.2319
  },
  {
    "close":0.2318
  },
  {
    "close":0.2317
  },
  {
    "close":0.23
  },
  {
    "close":0.2303
  },
  {
    "close":0.2295
  },
  {
    "close":0.2284
  },
  {
    "close":0.2294
  },
  {
    "close":0.2297
  },
  {
    "close":0.2293
  },
  {
    "close":0.2294
  },
  {
    "close":0.2296
  },
  {
    "close":0.2312
  },
  {
    "close":0.2311
  },
  {
    "close":0.2306
  },
  {
    "close":0.23
  },
  {
    "close":0.2311
  },
  {
    "close":0.23
  }
]