[
  {
    "close":0.3255
  },
  {
    "close":0.3253
  },
  {
    "close":0.3252
  },
  {
    "close":0.3253
  },
  {
    "close":0.3259
  },
  {
    "close":0.3275
  },
  {
    "close":0.3276
  },
  {
    "close":0.3271
  },
  {
    "close":0.3259
  },
  {
    "close":0.3263
  },
  {
    "close":0.326
  },
  {
    "close":0.3253
  },
  {
    "close":0.3256
  },
  {
    "close":0.3244
  },
  {
    "close":0.3246
  },
  {
    "close":0.3225
  },
  {
    "close":0.3231
  },
  {
    "close":0.3209
  },
  {
    "close":0.319
  },
  {
    "close":0.3201
  },
  {
    "close":0.3219
  },
  {
    "close":0.3217
  },
  {
    "close":0.3216
  },
  {
    "close":0.321
  },
  {
    "close":0.3232
  },
  {
    "close":0.3228
  },
  {
    "close":0.3221
  },
  {
    "close":0.3215
  },
  {
    "close":0.3228
  },
  {
    "close":0.3217
  }
]