[
  {
    "close":4.131
  },
  {
    "close":4.143
  },
  {
    "close":4.131
  },
  {
    "close":4.145
  },
  {
    "close":4.151
  },
  {
    "close":4.178
  },
  {
    "close":4.193
  },
  {
    "close":4.176
  },
  {
    "close":4.15
  },
  {
    "close":4.157
  },
  {
    "close":4.159
  },
  {
    "close":4.132
  },
  {
    "close":4.143
  },
  {
    "close":4.124
  },
  {
    "close":4.101
  },
  {
    "close":4.059
  },
  {
    "close":4.061
  },
  {
    "close":4.033
  },
  {
    "close":4.007
  },
  {
    "close":4.032
  },
  {
    "close":4.042
  },
  {
    "close":4.028
  },
  {
    "close":4.036
  },
  {
    "close":4.03
  },
  {
    "close":4.068
  },
  {
    "close":4.087
  },
  {
    "close":4.062
  },
  {
    "close":4.056
  },
  {
    "close":4.086
  },
  {
    "close":4.057
  }
]