[
  {
    "close":3.2708
  },
  {
    "close":3.2752
  },
  {
    "close":3.2662
  },
  {
    "close":3.2645
  },
  {
    "close":3.2648
  },
  {
    "close":3.2708
  },
  {
    "close":3.2837
  },
  {
    "close":3.2878
  },
  {
    "close":3.2777
  },
  {
    "close":3.2794
  },
  {
    "close":3.2783
  },
  {
    "close":3.2668
  },
  {
    "close":3.2742
  },
  {
    "close":3.2684
  },
  {
    "close":3.2593
  },
  {
    "close":3.2452
  },
  {
    "close":3.2502
  },
  {
    "close":3.2452
  },
  {
    "close":3.2352
  },
  {
    "close":3.248
  },
  {
    "close":3.2579
  },
  {
    "close":3.2522
  },
  {
    "close":3.2548
  },
  {
    "close":3.2516
  },
  {
    "close":3.2681
  },
  {
    "close":3.2781
  },
  {
    "close":3.2691
  },
  {
    "close":3.2731
  },
  {
    "close":3.2804
  },
  {
    "close":3.2648
  }
]